llm_prompt_shield/__init__.py
llm_prompt_shield/config.yaml
llm_prompt_shield/detector.py
llm_prompt_shield/policy.py
llm_prompt_shield/user_config.py
llm_prompt_shield/data/__init__.py
llm_prompt_shield/data/pattern_detector.yaml
llm_prompt_shield/data/patterns.yaml
llm_prompt_shield/integrations/__init__.py
llm_prompt_shield/integrations/autogen.py
llm_prompt_shield/integrations/langchain.py
llm_prompt_shield/layers/__init__.py
llm_prompt_shield/layers/pattern_detector.py
llm_prompt_shield/layers/semantic_analyzer.py
llm_prompt_shield-0.1.7.dist-info/licenses/LICENSE
llm_prompt_shield-0.1.7.dist-info/METADATA
llm_prompt_shield-0.1.7.dist-info/WHEEL
llm_prompt_shield-0.1.7.dist-info/top_level.txt
llm_prompt_shield-0.1.7.dist-info/RECORD
