Metadata-Version: 2.4
Name: llm-prompt-shield
Version: 0.1.7
Summary: Lightweight prompt injection detection and blocking
Home-page: https://github.com/rango-ramesh/llm-prompt-shield
Author: Rango Ramesh
Author-email: Rango Ramesh <rango@celestials.ai>
License: MIT License
Project-URL: Homepage, https://github.com/rango-ramesh/llm-prompt-shield
Project-URL: Repository, https://github.com/rango-ramesh/llm-prompt-shield
Project-URL: Documentation, https://github.com/rango-ramesh/llm-prompt-shield#readme
Project-URL: Bug Tracker, https://github.com/rango-ramesh/llm-prompt-shield/issues
Classifier: Development Status :: 3 - Alpha
Classifier: Intended Audience :: Developers
Classifier: License :: OSI Approved :: MIT License
Classifier: Operating System :: OS Independent
Classifier: Programming Language :: Python :: 3
Classifier: Programming Language :: Python :: 3.8
Classifier: Programming Language :: Python :: 3.9
Classifier: Programming Language :: Python :: 3.10
Classifier: Programming Language :: Python :: 3.11
Classifier: Topic :: Security
Requires-Python: >=3.8
License-File: LICENSE
Requires-Dist: PyYAML>=5.0.0
Requires-Dist: numpy>=1.20.0
Requires-Dist: joblib>=1.0.0
Requires-Dist: sentence-transformers>=2.0.0
Requires-Dist: transformers>=4.20.0
Requires-Dist: torch>=1.12.0
Provides-Extra: langchain
Requires-Dist: langchain>=0.0.200; extra == "langchain"
Provides-Extra: autogen
Requires-Dist: pyautogen>=0.2.0; extra == "autogen"
Provides-Extra: integrations
Requires-Dist: langchain>=0.0.200; extra == "integrations"
Requires-Dist: pyautogen>=0.2.0; extra == "integrations"
Dynamic: author
Dynamic: home-page
Dynamic: license-file
Dynamic: requires-python
